create_empty_image/LICENSE
create_empty_image/README.MD
create_empty_image/__init__.py
create_empty_image/requirements.txt
create_empty_image/thirdparty.json
create_empty_image-0.10.dist-info/LICENSE.rst
create_empty_image-0.10.dist-info/METADATA
create_empty_image-0.10.dist-info/WHEEL
create_empty_image-0.10.dist-info/top_level.txt
create_empty_image-0.10.dist-info/RECORD
